Workbook

Sheet Data
A1: product_id | B1: product_name | C1: main_category | D1: sub_category | E1: actual_price | F1: discounted_price | G1: discount_percentage | H1: savings_amount | I1: price_bucket | J1: rating | K1: rating_count | L1: sentiment_score | M1: sentiment_label
A2: B07JW9H4J1 | B2: Wayona Nylon Braided USB to Lightning Fast Charging and Data Sync Cable Compatible for iPhone 13, 12,11, X, 8, 7, 6, 5, iPad Air, Pro, Mini (3 FT Pack of 1, Grey) | C2: Computers&Accessories | D2: USBCables | E2: 1099 | F2: 399 | G2: 64 | H2: 700 | I2: Under 500 | J2: 4.2 | K2: 24269 | L2: 0.48194444 | M2: Positive
A3: B098NS6PVG | B3: Ambrane Unbreakable 60W / 3A Fast Charging 1.5m Braided Type C Cable for Smartphones, Tablets, Laptops & other Type C devices, PD Technology, 480Mbps Data Sync, Quick Charge 3.0 (RCT15A, Black) | C3: Computers&Accessories | D3: USBCables | E3: 349 | F3: 199 | G3: 43 | H3: 150 | I3: Under 500 | J3: 4 | K3: 43994 | L3: 0.27431818 | M3: Positive
A4: B096MSW6CT | B4: Sounce Fast Phone Charging Cable & Data Sync USB Cable Compatible for iPhone 13, 12,11, X, 8, 7, 6, 5, iPad Air, Pro, Mini & iOS Devices | C4: Computers&Accessories | D4: USBCables | E4: 1899 | F4: 199 | G4: 90 | H4: 1700 | I4: Under 500 | J4: 3.9 | K4: 7928 | L4: 0.6 | M4: Positive
A5: B08HDJ86NZ | B5: boAt Deuce USB 300 2 in 1 Type-C & Micro USB Stress Resistant, Tangle-Free, Sturdy Cable with 3A Fast Charging & 480mbps Data Transmission, 10000+ Bends Lifespan and Extended 1.5m Length(Martian Red) | C5: Computers&Accessories | D5: USBCables | E5: 699 | F5: 329 | G5: 53 | H5: 370 | I5: Under 500 | J5: 4.2 | K5: 94363 | L5: 0.24037037 | M5: Positive
A6: B08CF3B7N1 | B6: Portronics Konnect L 1.2M Fast Charging 3A 8 Pin USB Cable with Charge & Sync Function for iPhone, iPad (Grey) | C6: Computers&Accessories | D6: USBCables | E6: 399 | F6: 154 | G6: 61 | H6: 245 | I6: Under 500 | J6: 4.2 | K6: 16905 | L6: 0.26274038 | M6: Positive
A7: B08Y1TFSP6 | B7: pTron Solero TB301 3A Type-C Data and Fast Charging Cable, Made in India, 480Mbps Data Sync, Strong and Durable 1.5-Meter Nylon Braided USB Cable for Type-C Devices for Charging Adapter (Black) | C7: Computers&Accessories | D7: USBCables | E7: 1000 | F7: 149 | G7: 85 | H7: 851 | I7: Under 500 | J7: 3.9 | K7: 24871 | L7: 0.48666667 | M7: Positive
A8: B08WRWPM22 | B8: boAt Micro USB 55 Tangle-free, Sturdy Micro USB Cable with 3A Fast Charging & 480mbps Data Transmission (Black) | C8: Computers&Accessories | D8: USBCables | E8: 499 | F8: 176.63 | G8: 65 | H8: 322.37 | I8: Under 500 | J8: 4.1 | K8: 15188 | L8: 0.67777778 | M8: Positive
A9: B08DDRGWTJ | B9: MI Usb Type-C Cable Smartphone (Black) | C9: Computers&Accessories | D9: USBCables | E9: 299 | F9: 229 | G9: 23 | H9: 70 | I9: Under 500 | J9: 4.3 | K9: 30411 | L9: 0.37604167 | M9: Positive
A10: B008IFXQFU | B10: TP-Link USB WiFi Adapter for PC(TL-WN725N), N150 Wireless Network Adapter for Desktop - Nano Size WiFi Dongle Compatible with Windows 11/10/7/8/8.1/XP/ Mac OS 10.9-10.15 Linux Kernel 2.6.18-4.4.3 | C10: Computers&Accessories | D10: WirelessUSBAdapters | E10: 999 | F10: 499 | G10: 50 | H10: 500 | I10: Under 500 | J10: 4.2 | K10: 179691 | L10: 0.27894067 | M10: Positive
A11: B082LZGK39 | B11: Ambrane Unbreakable 60W / 3A Fast Charging 1.5m Braided Micro USB Cable for Smartphones, Tablets, Laptops & Other Micro USB Devices, 480Mbps Data Sync, Quick Charge 3.0 (RCM15, Black) | C11: Computers&Accessories | D11: USBCables | E11: 299 | F11: 199 | G11: 33 | H11: 100 | I11: Under 500 | J11: 4 | K11: 43994 | L11: 0.27431818 | M11: Positive
A12: B08CF3D7QR | B12: Portronics Konnect L POR-1081 Fast Charging 3A Type-C Cable 1.2Meter with Charge & Sync Function for All Type-C Devices (Grey) | C12: Computers&Accessories | D12: USBCables | E12: 339 | F12: 154 | G12: 55 | H12: 185 | I12: Under 500 | J12: 4.3 | K12: 13391 | L12: 0.134 | M12: Positive
A13: B0789LZTCJ | B13: boAt Rugged v3 Extra Tough Unbreakable Braided Micro USB Cable 1.5 Meter (Black) | C13: Computers&Accessories | D13: USBCables | E13: 799 | F13: 299 | G13: 63 | H13: 500 | I13: Under 500 | J13: 4.2 | K13: 94363 | L13: 0.24037037 | M13: Positive
... A1349: B01486F4G6 | B1349: Borosil Jumbo 1000-Watt Grill Sandwich Maker (Black) | C1349: Home&Kitchen | D1349: SandwichMakers | E1349: 3690 | F1349: 2863 | G1349: 22 | H1349: 827 | I1349: 1500-5000 | J1349: 4.3 | K1349: 6987 | L1349: 0.31813725 | M1349: Positive

Sheet Summary
A1: Amazon Product Analytics — Summary
A3: Category | B3: Num Products | C3: Avg Discounted Price | D3: Avg Discount % | E3: Avg Rating | F3: Total Reviews
A4: Car&Motorbike | B4: =COUNTIF(Data!$C$2:$C$1349,A4) -> 1 | C4: =ROUND(AVERAGEIF(Data!$C$2:$C$1349,A4,Data!$F$2:$F$1349),0) -> 2339 | D4: =ROUND(AVERAGEIF(Data!$C$2:$C$1349,A4,Data!$G$2:$G$1349),1) -> 42 | E4: =ROUND(AVERAGEIF(Data!$C$2:$C$1349,A4,Data!$J$2:$J$1349),2) -> 3.8 | F4: =SUMIF(Data!$C$2:$C$1349,A4,Data!$K$2:$K$1349) -> 1118
A5: Computers&Accessories | B5: =COUNTIF(Data!$C$2:$C$1349,A5) -> 373 | C5: =ROUND(AVERAGEIF(Data!$C$2:$C$1349,A5,Data!$F$2:$F$1349),0) -> 951 | D5: =ROUND(AVERAGEIF(Data!$C$2:$C$1349,A5,Data!$G$2:$G$1349),1) -> 53.1 | E5: =ROUND(AVERAGEIF(Data!$C$2:$C$1349,A5,Data!$J$2:$J$1349),2) -> 4.15 | F5: =SUMIF(Data!$C$2:$C$1349,A5,Data!$K$2:$K$1349) -> 6335177
A6: Electronics | B6: =COUNTIF(Data!$C$2:$C$1349,A6) -> 490 | C6: =ROUND(AVERAGEIF(Data!$C$2:$C$1349,A6,Data!$F$2:$F$1349),0) -> 6226 | D6: =ROUND(AVERAGEIF(Data!$C$2:$C$1349,A6,Data!$G$2:$G$1349),1) -> 49.9 | E6: =ROUND(AVERAGEIF(Data!$C$2:$C$1349,A6,Data!$J$2:$J$1349),2) -> 4.08 | F6: =SUMIF(Data!$C$2:$C$1349,A6,Data!$K$2:$K$1349) -> 14208406
A7: Health&PersonalCare | B7: =COUNTIF(Data!$C$2:$C$1349,A7) -> 1 | C7: =ROUND(AVERAGEIF(Data!$C$2:$C$1349,A7,Data!$F$2:$F$1349),0) -> 899 | D7: =ROUND(AVERAGEIF(Data!$C$2:$C$1349,A7,Data!$G$2:$G$1349),1) -> 53 | E7: =ROUND(AVERAGEIF(Data!$C$2:$C$1349,A7,Data!$J$2:$J$1349),2) -> 4 | F7: =SUMIF(Data!$C$2:$C$1349,A7,Data!$K$2:$K$1349) -> 3663
A8: Home&Kitchen | B8: =COUNTIF(Data!$C$2:$C$1349,A8) -> 447 | C8: =ROUND(AVERAGEIF(Data!$C$2:$C$1349,A8,Data!$F$2:$F$1349),0) -> 2331 | D8: =ROUND(AVERAGEIF(Data!$C$2:$C$1349,A8,Data!$G$2:$G$1349),1) -> 40.2 | E8: =ROUND(AVERAGEIF(Data!$C$2:$C$1349,A8,Data!$J$2:$J$1349),2) -> 4.04 | F8: =SUMIF(Data!$C$2:$C$1349,A8,Data!$K$2:$K$1349) -> 2990077
A9: HomeImprovement | B9: =COUNTIF(Data!$C$2:$C$1349,A9) -> 2 | C9: =ROUND(AVERAGEIF(Data!$C$2:$C$1349,A9,Data!$F$2:$F$1349),0) -> 337 | D9: =ROUND(AVERAGEIF(Data!$C$2:$C$1349,A9,Data!$G$2:$G$1349),1) -> 57.5 | E9: =ROUND(AVERAGEIF(Data!$C$2:$C$1349,A9,Data!$J$2:$J$1349),2) -> 4.25 | F9: =SUMIF(Data!$C$2:$C$1349,A9,Data!$K$2:$K$1349) -> 8566
A10: MusicalInstruments | B10: =COUNTIF(Data!$C$2:$C$1349,A10) -> 2 | C10: =ROUND(AVERAGEIF(Data!$C$2:$C$1349,A10,Data!$F$2:$F$1349),0) -> 638 | D10: =ROUND(AVERAGEIF(Data!$C$2:$C$1349,A10,Data!$G$2:$G$1349),1) -> 46 | E10: =ROUND(AVERAGEIF(Data!$C$2:$C$1349,A10,Data!$J$2:$J$1349),2) -> 3.9 | F10: =SUMIF(Data!$C$2:$C$1349,A10,Data!$K$2:$K$1349) -> 88882
A11: OfficeProducts | B11: =COUNTIF(Data!$C$2:$C$1349,A11) -> 31 | C11: =ROUND(AVERAGEIF(Data!$C$2:$C$1349,A11,Data!$F$2:$F$1349),0) -> 302 | D11: =ROUND(AVERAGEIF(Data!$C$2:$C$1349,A11,Data!$G$2:$G$1349),1) -> 12.4 | E11: =ROUND(AVERAGEIF(Data!$C$2:$C$1349,A11,Data!$J$2:$J$1349),2) -> 4.31 | F11: =SUMIF(Data!$C$2:$C$1349,A11,Data!$K$2:$K$1349) -> 149675
A12: Toys&Games | B12: =COUNTIF(Data!$C$2:$C$1349,A12) -> 1 | C12: =ROUND(AVERAGEIF(Data!$C$2:$C$1349,A12,Data!$F$2:$F$1349),0) -> 150 | D12: =ROUND(AVERAGEIF(Data!$C$2:$C$1349,A12,Data!$G$2:$G$1349),1) -> 0 | E12: =ROUND(AVERAGEIF(Data!$C$2:$C$1349,A12,Data!$J$2:$J$1349),2) -> 4.3 | F12: =SUMIF(Data!$C$2:$C$1349,A12,Data!$K$2:$K$1349) -> 15867
A15: Overall KPIs
A16: Total Products | B16: =COUNTA(Data!A2:A1349) -> 1348
A17: Average Rating (all products) | B17: =ROUND(AVERAGE(Data!J2:J1349),2) -> 4.09
A18: Average Discount % | B18: =ROUND(AVERAGE(Data!G2:G1349),1) -> 46.7
A19: Total Reviews | B19: =SUM(Data!K2:K1349) -> 23801431

Sheet Sentiment
A1: Review Sentiment vs Star Rating
A3: Sentiment Label | B3: Num Products | C3: Avg Star Rating
A4: Positive | B4: =COUNTIF(Data!$M$2:$M$1349,A4) -> 1239 | C4: =ROUND(AVERAGEIF(Data!$M$2:$M$1349,A4,Data!$J$2:$J$1349),2) -> 4.11
A5: Neutral | B5: =COUNTIF(Data!$M$2:$M$1349,A5) -> 96 | C5: =ROUND(AVERAGEIF(Data!$M$2:$M$1349,A5,Data!$J$2:$J$1349),2) -> 3.89
A6: Negative | B6: =COUNTIF(Data!$M$2:$M$1349,A6) -> 13 | C6: =ROUND(AVERAGEIF(Data!$M$2:$M$1349,A6,Data!$J$2:$J$1349),2) -> 3.95
